openai_utilities/__init__.py
openai_utilities/chat.py
openai_utilities/embeddings.py
openai_utilities/retryutils.py
openai_utilities/tokenutils.py
openai_utilities-0.2.6.dist-info/LICENSE
openai_utilities-0.2.6.dist-info/METADATA
openai_utilities-0.2.6.dist-info/WHEEL
openai_utilities-0.2.6.dist-info/top_level.txt
openai_utilities-0.2.6.dist-info/RECORD
