Metadata-Version: 2.1
Name: openai-utilities
Version: 0.2.6
Summary: Wrapper on top of openai python SDK primarily to interface with openai and anyscale public endpoints.
Home-page: https://github.com/soumitsalman/openai-utilities
Author: Soumit Salman Rahman
Author-email: soumitsr@gmail.com
License: MIT
Keywords: openai anyscale tiktoken chatgpt chatbot
License-File: LICENSE
Requires-Dist: openai
Requires-Dist: tiktoken
Requires-Dist: icecream
Requires-Dist: numpy
Requires-Dist: transformers
Requires-Dist: scipy
